Workbook

Sheet README
B2: Finance Controller Practical Case Study
B3: ABC Manufacturing Ltd. — FY 2025-26
B5: Purpose | C5: Practice taking a raw Trial Balance through to a full financial analysis, the way a Finance Controller interview case study is run.
B6: Currency | C6: ₹ Million (INR millions)
B8: Tab | C8: What it contains
B9: 1. Trial Balance (Raw) | C9: The Trial Balance as originally given — deliberately out of balance by ₹65M, to practice the investigate-don't-force approach.
B10: 2. Trial Balance (Corrected) | C10: Same Trial Balance after the missing ₹65M of PPE is identified and posted. Debits = Credits here.
B11: 3. P&L | C11: Revenue through Net Profit, built entirely with formulas off the corrected Trial Balance.
B12: 4. Balance Sheet | C12: Assets, Liabilities and Equity, linked to the P&L and Trial Balance.
B13: 5. Ratios & Working Capital | C13: Profitability, liquidity and efficiency ratios, calculated from the P&L and Balance Sheet.
B14: 6. Variance Analysis | C14: Prior year vs current year comparison — the 'revenue up, profit down' scenario.
B15: 7. Control Checks | C15: Three checks that must equal zero before you'd ever present these statements: TB difference, Balance Sheet difference, P&L tie-out.
B17: How to use it | C17: Start on Tab 1. Try to spot the imbalance yourself before opening Tab 2. Then trace how the corrected Trial Balance flows into the P&L, Balance Sheet, and ratios — every number is a live formula, so you can change an input on Tab 2 and watch it ripple through.
B18: Color key | C18: Blue = input / given number. Black = formula (do not overtype). Yellow fill = a control check result.

Sheet 1. Trial Balance (Raw)
B2: Trial Balance (As Originally Given) — Practice: find the imbalance
B4: Account | C4: Debit (₹M) | D4: Credit (₹M)
B5: Cash & Bank | C5: 25
B6: Accounts Receivable | C6: 45
B7: Inventory | C7: 60
B8: Prepaid Expenses | C8: 10
B9: Property, Plant & Equipment | C9: 150
B10: Accumulated Depreciation | D10: 30
B11: Accounts Payable | D11: 50
B12: Accrued Expenses | D12: 15
B13: Long-Term Loan | D13: 80
B14: Share Capital | D14: 100
B15: Retained Earnings - Opening | D15: 25
B16: Revenue | D16: 300
B17: Cost of Goods Sold | C17: 170
B18: Employee Expenses | C18: 35
B19: Other Operating Expenses | C19: 20
B20: Depreciation Expense | C20: 15
B21: Finance Cost | C21: 8
B22: Tax Expense | C22: 7
B23: Total | C23: =SUM(C5:C22) -> 545 | D23: =SUM(D5:D22) -> 600
B25: Difference (Debit - Credit) | C25: =C23-D23 -> -55
B27: Note: This Trial Balance does not balance. As a Controller, investigate the gap (missing account, incorrect posting, opening balance issue) rather than forcing it. See Tab 2 for the resolution.

Sheet 2. Trial Balance (Corrected)
B2: Trial Balance (Corrected) — Missing PPE of ₹65M identified & posted
B4: Account | C4: Debit (₹M) | D4: Credit (₹M)
B5: Cash & Bank | C5: 25
B6: Accounts Receivable | C6: 45
B7: Inventory | C7: 60
B8: Prepaid Expenses | C8: 10
B9: Property, Plant & Equipment | C9: 215
B10: Accumulated Depreciation | D10: 30
B11: Accounts Payable | D11: 50
B12: Accrued Expenses | D12: 15
B13: Long-Term Loan | D13: 80
B14: Share Capital | D14: 100
B15: Retained Earnings - Opening | D15: 25
B16: Revenue | D16: 300
B17: Cost of Goods Sold | C17: 170
B18: Employee Expenses | C18: 35
B19: Other Operating Expenses | C19: 20
B20: Depreciation Expense | C20: 15
B21: Finance Cost | C21: 8
B22: Tax Expense | C22: 7
B23: Total | C23: =SUM(C5:C22) -> 610 | D23: =SUM(D5:D22) -> 600
B25: Investigation finding: an additional ₹65M of fixed assets had been omitted from the original Trial Balance. Corrected PPE = ₹150M + ₹65M = ₹215M. This closes most of the gap, but a further ₹10M difference remains on this Trial Balance (see Tab 7: Control Checks) — a second item for the reader to trace before finalizing the statements. A Controller does not force this to zero.

Sheet 3. P&L
B2: Profit & Loss Statement — FY 2025-26
B4: Line Item | C4: ₹M | D4: % of Revenue
B5: Revenue | C5: ='2. Trial Balance (Corrected)'!D16 -> 300 | D5: =C5/$C$5 -> 1
B6: Less: Cost of Goods Sold | C6: =-'2. Trial Balance (Corrected)'!C17 -> -170
B7: Gross Profit | C7: =C5+C6 -> 130 | D7: =C7/$C$5 -> 0.43333333
B9: Less: Employee Expenses | C9: =-'2. Trial Balance (Corrected)'!C18 -> -35
B10: Less: Other Operating Expenses | C10: =-'2. Trial Balance (Corrected)'!C19 -> -20
B11: EBITDA | C11: =C7+C9+C10 -> 75 | D11: =C11/$C$5 -> 0.25
B13: Less: Depreciation & Amortization | C13: =-'2. Trial Balance (Corrected)'!C20 -> -15
B14: EBIT | C14: =C11+C13 -> 60 | D14: =C14/$C$5 -> 0.2
B16: Less: Finance Cost | C16: =-'2. Trial Balance (Corrected)'!C21 -> -8
B17: Profit Before Tax (PBT) | C17: =C14+C16 -> 52 | D17: =C17/$C$5 -> 0.17333333
B19: Less: Tax Expense | C19: =-'2. Trial Balance (Corrected)'!C22 -> -7
B20: Net Profit | C20: =C17+C19 -> 45 | D20: =C20/$C$5 -> 0.15
B23: EBITDA − D&A = EBIT. EBITDA reflects operating profitability before financing structure, tax, and depreciation policy — but it is not cash flow, since it ignores working capital, capex, interest and tax.

Sheet 4. Balance Sheet
B2: Balance Sheet — Assets | E2: Balance Sheet — Liabilities & Equity
B4: Assets | C4: ₹M | E4: Liabilities & Equity | F4: ₹M
B5: Cash & Bank | C5: ='2. Trial Balance (Corrected)'!C5 -> 25 | E5: Accounts Payable | F5: ='2. Trial Balance (Corrected)'!D11 -> 50
B6: Accounts Receivable | C6: ='2. Trial Balance (Corrected)'!C6 -> 45 | E6: Accrued Expenses | F6: ='2. Trial Balance (Corrected)'!D12 -> 15
B7: Inventory | C7: ='2. Trial Balance (Corrected)'!C7 -> 60 | E7: Total Current Liabilities | F7: =SUM(F5:F6) -> 65
B8: Prepaid Expenses | C8: ='2. Trial Balance (Corrected)'!C8 -> 10
B9: Total Current Assets | C9: =SUM(C5:C8) -> 140 | E9: Long-Term Loan | F9: ='2. Trial Balance (Corrected)'!D13 -> 80
E10: Total Liabilities | F10: =F7+F9 -> 145
B11: Property, Plant & Equipment (Gross) | C11: ='2. Trial Balance (Corrected)'!C9 -> 215
B12: Less: Accumulated Depreciation | C12: =-'2. Trial Balance (Corrected)'!D10 -> -30 | E12: Share Capital | F12: ='2. Trial Balance (Corrected)'!D14 -> 100
B13: Net PPE | C13: =C11+C12 -> 185 | E13: Opening Retained Earnings | F13: ='2. Trial Balance (Corrected)'!D15 -> 25
E14: Current-Year Profit | F14: ='3. P&L'!C20 -> 45
B15: Total Assets | C15: =C9+C13 -> 325 | E15: Total Equity | F15: =F12+F13+F14 -> 170
E17: Total Liabilities + Equity | F17: =F10+F15 -> 315
B19: Assets = Liabilities + Equity. If Total Assets (left) does not equal Total Liabilities + Equity (right), a Controller investigates the gap via reconciliation, journal entries, opening balances or suspense accounts — see Tab 7: Control Checks.

Sheet 5. Ratios & Working Capital
B2: Ratios & Working Capital Analysis
B4: Metric | C4: Value
B5: Gross Margin | C5: ='3. P&L'!C7/'3. P&L'!C5 -> 0.43333333
B6: EBITDA Margin | C6: ='3. P&L'!C11/'3. P&L'!C5 -> 0.25
B7: EBIT Margin | C7: ='3. P&L'!C14/'3. P&L'!C5 -> 0.2
B8: Net Profit Margin | C8: ='3. P&L'!C20/'3. P&L'!C5 -> 0.15
B10: Working Capital (Current Assets - Current Liabilities) | C10: ='4. Balance Sheet'!C9-'4. Balance Sheet'!F7 -> 75
B11: Current Ratio (Current Assets / Current Liabilities) | C11: ='4. Balance Sheet'!C9/'4. Balance Sheet'!F7 -> 2.1538462
B13: Debt-to-Equity (Long-Term Loan / Total Equity) | C13: ='2. Trial Balance (Corrected)'!D13/'4. Balance Sheet'!F15 -> 0.47058824
B14: Net Debt / EBITDA | C14: =('2. Trial Balance (Corrected)'!D13-'4. Balance Sheet'!C5)/'3. P&L'!C11 -> 0.73333333
B17: Controller interpretation: a healthy current ratio (>1.5x) supports short-term solvency, but should be read alongside the quality of receivables and inventory — not on its own.

Sheet 6. Variance Analysis
B2: Scenario: 'Revenue increased, so we must be performing better' — a Controller checks the variance first
B4: Metric | C4: Prior Year (₹M) | D4: Current Year (₹M) | E4: Variance (₹M)
B5: Revenue | C5: 260 | D5: 300 | E5: =D5-C5 -> 40
B6: Gross Profit | C6: 120 | D6: 130 | E6: =D6-C6 -> 10
B7: EBITDA | C7: 70 | D7: 75 | E7: =D7-C7 -> 5
B8: EBIT | C8: 58 | D8: 60 | E8: =D8-C8 -> 2
B9: Net Profit | C9: 48 | D9: 45 | E9: =D9-C9 -> -3
B12: Revenue grew ₹40M but Net Profit fell ₹3M. Root-cause checklist to walk through out loud in an interview: COGS increase → gross margin down · employee/opex increase → EBITDA down · higher depreciation → EBIT down · higher finance cost or tax → net profit down · one-off/exceptional items.

Sheet 7. Control Checks
B2: Control Checks — every result below must equal zero
B4: Check | C4: Result | D4: Status
B5: Trial Balance (Raw) — Debit minus Credit | C5: ='1. Trial Balance (Raw)'!C23-'1. Trial Balance (Raw)'!D23 -> -55 | D5: =IF(C5=0,"OK","INVESTIGATE") -> INVESTIGATE
B6: Trial Balance (Corrected) — Debit minus Credit | C6: ='2. Trial Balance (Corrected)'!C23-'2. Trial Balance (Corrected)'!D23 -> 10 | D6: =IF(C6=0,"OK","INVESTIGATE") -> INVESTIGATE
B7: Balance Sheet — Total Assets minus (Liabilities + Equity) | C7: ='4. Balance Sheet'!C15-'4. Balance Sheet'!F17 -> 10 | D7: =IF(C7=0,"OK","INVESTIGATE") -> INVESTIGATE
B8: P&L Tie-out — Revenue less all deductions minus Net Profit | C8: =('3. P&L'!C5-'3. P&L'!C7+'3. P&L'!C7-'3. P&L'!C11+'3. P&L'!C11-'3. P&L'!C14+'3. P&L'!C14-'3. P&L'!C17+'3. P&L'!C17-'3. P&L'!C20)-('3. P&L'!C5-'3. P&L'!C20) -> 0 | D8: =IF(C8=0,"OK","INVESTIGATE") -> OK
B11: Interview point: the Raw Trial Balance shows INVESTIGATE by design (the missing ₹65M PPE). After that correction, a further ₹10M difference remains on both the Trial Balance and the Balance Sheet checks — also by design. Use this as a live practice exercise: trace which account is still misstated (a common answer is an unrecorded opening balance, dividend/drawing, or a missed accrual) rather than plugging the gap. The P&L tie-out check is clean (OK) since it doesn't depend on this item.
