Workbook

Sheet Instructions
A1: Finance Controller Practical Excel Case Study
A2: Objective | B2: Take a Trial Balance through classification, P&L, Balance Sheet, controls, ratios and management analysis.
A3: Suggested interview flow | B3: Trial Balance → Adjustments → P&L → EBITDA/EBIT → Balance Sheet → Controls → Ratios → Scenario Analysis.
A4: Important | B4: Do not force a Balance Sheet to balance. Investigate differences through reconciliations and missing/incorrect postings.
A5: Excel skills demonstrated | B5: SUM, SUMIFS, XLOOKUP, IF, IFERROR, Pivot Tables, Conditional Formatting, charts and control checks.

Sheet Trial Balance
A1: Account | B1: Debit (₹M) | C1: Credit (₹M) | D1: Classification | E1: Notes
A2: Cash & Bank | B2: 25 | D2: Current Asset
A3: Accounts Receivable | B3: 45 | D3: Current Asset
A4: Inventory | B4: 60 | D4: Current Asset
A5: Prepaid Expenses | B5: 10 | D5: Current Asset
A6: Property, Plant & Equipment | B6: 215 | D6: Non-current Asset | E6: Includes corrected ₹65M omission
A7: Accumulated Depreciation | C7: 30 | D7: Contra Asset
A8: Accounts Payable | C8: 50 | D8: Current Liability
A9: Accrued Expenses | C9: 15 | D9: Current Liability
A10: Long-Term Loan | C10: 80 | D10: Non-current Liability
A11: Share Capital | C11: 100 | D11: Equity
A12: Retained Earnings – Opening | C12: 25 | D12: Equity
A13: Revenue | C13: 300 | D13: Revenue
A14: Cost of Goods Sold | B14: 170 | D14: P&L Expense
A15: Employee Expenses | B15: 35 | D15: P&L Expense
A16: Other Operating Expenses | B16: 20 | D16: P&L Expense
A17: Depreciation Expense | B17: 15 | D17: P&L Expense
A18: Finance Cost | B18: 8 | D18: P&L Expense
A19: Tax Expense | B19: 7 | D19: P&L Expense
A20: Total | B20: =SUM(B2:B19) -> 610 | C20: =SUM(C2:C19) -> 600
A21: TB Difference | B21: =B20-C20 -> 10 | D21: Expected: 0

Sheet P&L
A1: P&L Item | B1: Amount (₹M) | C1: Formula / Source
A2: Revenue | B2: =SUMIF('Trial Balance'!D2:D19,"Revenue",'Trial Balance'!B2:B19)+SUMIF('Trial Balance'!D2:D19,"Revenue",'Trial Balance'!C2:C19) -> 300 | C2: Trial Balance
A3: COGS | B3: =SUMIF('Trial Balance'!D2:D19,"P&L Expense",'Trial Balance'!B2:B19)-SUMIFS('Trial Balance'!B2:B19,'Trial Balance'!A2:A19,"Employee Expenses")-SUMIFS('Trial Balance'!B2:B19,'Trial Balance'!A2:A19,"Other Operating Expenses")-SUMIFS('Trial Balance'!B2:B19,'Trial Balance'!A2:A19,"Depreciation Expense")-SUMIFS('Trial Balance'!B2:B19,'Trial Balance'!A2:A19,"Finance Cost")-SUMIFS('Trial Balance'!B2:B19,'Trial Balance'!A2:A19,"Tax Expense") -> 170 | C3: Trial Balance
A4: Gross Profit | B4: =B2-B3 -> 130 | C4: Revenue - COGS
A5: Employee Expenses | B5: =SUMIFS('Trial Balance'!B2:B19,'Trial Balance'!A2:A19,"Employee Expenses") -> 35 | C5: Trial Balance
A6: Other Operating Expenses | B6: =SUMIFS('Trial Balance'!B2:B19,'Trial Balance'!A2:A19,"Other Operating Expenses") -> 20 | C6: Trial Balance
A7: EBITDA | B7: =B4-B5-B6 -> 75 | C7: Gross Profit - Operating Expenses
A8: Depreciation & Amortization | B8: =SUMIFS('Trial Balance'!B2:B19,'Trial Balance'!A2:A19,"Depreciation Expense") -> 15 | C8: Trial Balance
A9: EBIT | B9: =B7-B8 -> 60 | C9: EBITDA - D&A
A10: Finance Cost | B10: =SUMIFS('Trial Balance'!B2:B19,'Trial Balance'!A2:A19,"Finance Cost") -> 8 | C10: Trial Balance
A11: PBT | B11: =B9-B10 -> 52 | C11: EBIT - Finance Cost
A12: Tax | B12: =SUMIFS('Trial Balance'!B2:B19,'Trial Balance'!A2:A19,"Tax Expense") -> 7 | C12: Trial Balance
A13: Net Profit | B13: =B11-B12 -> 45 | C13: PBT - Tax

Sheet Balance Sheet
A1: Balance Sheet Item | B1: Amount (₹M) | C1: Formula / Source
A2: Cash & Bank | B2: ='Trial Balance'!B2 -> 25 | C2: Trial Balance
A3: Accounts Receivable | B3: ='Trial Balance'!B3 -> 45 | C3: Trial Balance
A4: Inventory | B4: ='Trial Balance'!B4 -> 60 | C4: Trial Balance
A5: Prepaid Expenses | B5: ='Trial Balance'!B5 -> 10 | C5: Trial Balance
A6: Current Assets | B6: =SUM(B2:B5) -> 140 | C6: Sum
A7: Gross PPE | B7: ='Trial Balance'!B6 -> 215 | C7: Trial Balance
A8: Accumulated Depreciation | B8: ='Trial Balance'!C7 -> 30 | C8: Trial Balance
A9: Net PPE | B9: =B7-B8 -> 185 | C9: Gross PPE - Accumulated Depreciation
A10: Total Assets | B10: =B6+B9 -> 325 | C10: Current Assets + Net PPE
A11: Accounts Payable | B11: ='Trial Balance'!C8 -> 50 | C11: Trial Balance
A12: Accrued Expenses | B12: ='Trial Balance'!C9 -> 15 | C12: Trial Balance
A13: Current Liabilities | B13: =SUM(B11:B12) -> 65 | C13: Sum
A14: Long-Term Loan | B14: ='Trial Balance'!C10 -> 80 | C14: Trial Balance
A15: Total Liabilities | B15: =B13+B14 -> 145 | C15: Current + Long-term
A16: Share Capital | B16: ='Trial Balance'!C11 -> 100 | C16: Trial Balance
A17: Opening Retained Earnings | B17: ='Trial Balance'!C12 -> 25 | C17: Trial Balance
A18: Current-Year Profit | B18: ='P&L'!B14 -> 0 | C18: P&L Net Profit
A19: Total Equity | B19: =SUM(B16:B18) -> 125 | C19: Sum
A20: Liabilities + Equity | B20: =B15+B19 -> 270 | C20: Total Liabilities + Equity
A21: Balance Sheet Difference | B21: =B10-B20 -> 55 | C21: Expected: 0

Sheet Controls & Ratios
A1: Control / Ratio | B1: Result | C1: Expected / Interpretation
A2: Trial Balance Difference | B2: ='Trial Balance'!B21 -> 10 | C2: 0
A3: Balance Sheet Difference | B3: ='Balance Sheet'!B21 -> 55 | C3: 0
A4: Gross Margin | B4: ='P&L'!B4/'P&L'!B2 -> 0.43333333 | C4: Higher is generally better; investigate movement
A5: EBITDA Margin | B5: ='P&L'!B7/'P&L'!B2 -> 0.25 | C5: Operating profitability
A6: EBIT Margin | B6: ='P&L'!B9/'P&L'!B2 -> 0.2 | C6: Profitability after D&A
A7: Net Profit Margin | B7: ='P&L'!B14/'P&L'!B2 -> 0 | C7: Bottom-line profitability
A8: Working Capital | B8: ='Balance Sheet'!B6-'Balance Sheet'!B13 -> 75 | C8: Current Assets - Current Liabilities
A9: Current Ratio | B9: ='Balance Sheet'!B6/'Balance Sheet'!B13 -> 2.1538462 | C9: Liquidity indicator
A10: Debt / Equity | B10: ='Balance Sheet'!B14/'Balance Sheet'!B19 -> 0.64 | C10: Leverage indicator
A11: Net Debt / EBITDA | B11: =('Balance Sheet'!B14-'Balance Sheet'!B2)/'P&L'!B7 -> 0.73333333 | C11: Lower generally indicates lower leverage

Sheet Scenario Analysis
A1: Metric | B1: Previous Year (₹M) | C1: Current Year (₹M) | D1: Variance (₹M) | E1: Variance % | F1: Controller Comment
A2: Revenue | B2: 260 | C2: 300 | D2: =C2-B2 -> 40 | E2: =D2/B2 -> 0.15384615 | F2: Revenue growth
A3: Gross Profit | B3: 120 | C3: 130 | D3: =C3-B3 -> 10 | E3: =D3/B3 -> 0.083333333 | F3: Assess gross margin
A4: EBITDA | B4: 70 | C4: 75 | D4: =C4-B4 -> 5 | E4: =D4/B4 -> 0.071428571 | F4: Assess operating leverage
A5: EBIT | B5: 58 | C5: 60 | D5: =C5-B5 -> 2 | E5: =D5/B5 -> 0.034482759 | F5: Assess D&A impact
A6: Net Profit | B6: 48 | C6: 45 | D6: =C6-B6 -> -3 | E6: =D6/B6 -> -0.0625 | F6: Profit declined despite revenue growth
A8: Scenario question | F8: Revenue increased but net profit decreased. Investigate COGS, operating expenses, D&A, finance costs, tax and one-off items.

Sheet Management Summary
A1: Management KPI | B1: Value
A2: Revenue | B2: ='P&L'!B2 -> 300
A3: Gross Profit | B3: ='P&L'!B4 -> 130
A4: EBITDA | B4: ='P&L'!B7 -> 75
A5: EBITDA Margin | B5: ='Controls & Ratios'!B5 -> 0.25
A6: EBIT | B6: ='P&L'!B9 -> 60
A7: Net Profit | B7: ='P&L'!B14 -> 0
A8: Net Profit Margin | B8: ='Controls & Ratios'!B7 -> 0
A9: Working Capital | B9: ='Controls & Ratios'!B8 -> 75
A10: Current Ratio | B10: ='Controls & Ratios'!B9 -> 2.1538462
A11: TB Check | B11: ='Controls & Ratios'!B2 -> 10
A12: BS Check | B12: ='Controls & Ratios'!B3 -> 55
